eripotter_common/__init__.py
eripotter_common/database/__init__.py
eripotter_common/database/base.py
eripotter_common/database/config.py
eripotter_common/database/session.py
eripotter_common/security/__init__.py
eripotter_common/security/security.py
eripotter_common/www/__init__.py
eripotter_common/www/env.py
eripotter_common-0.1.4.dist-info/METADATA
eripotter_common-0.1.4.dist-info/WHEEL
eripotter_common-0.1.4.dist-info/licenses/LICENSE
eripotter_common-0.1.4.dist-info/RECORD
