Metadata-Version: 2.4
Name: eripotter-common
Version: 0.1.4
Summary: Common utilities for EriPotter microservices
Project-URL: Homepage, https://eripotter.com
Project-URL: Repository, https://github.com/eripotter/eripotter-common
Author: EriPotter Team
License-Expression: MIT
License-File: LICENSE
Classifier: Development Status :: 3 - Alpha
Classifier: Intended Audience :: Developers
Classifier: License :: OSI Approved :: MIT License
Classifier: Programming Language :: Python :: 3
Classifier: Programming Language :: Python :: 3.9
Classifier: Programming Language :: Python :: 3.10
Classifier: Programming Language :: Python :: 3.11
Requires-Python: >=3.9
Requires-Dist: asyncpg>=0.28.0
Requires-Dist: bcrypt>=4.0.1
Requires-Dist: fastapi>=0.100.0
Requires-Dist: httpx>=0.24.0
Requires-Dist: passlib>=1.7.4
Requires-Dist: pydantic>=2.0.0
Requires-Dist: pyjwt>=2.8.0
Requires-Dist: python-dotenv>=1.0.0
Requires-Dist: sqlalchemy>=2.0.0
Provides-Extra: test
Requires-Dist: pytest-asyncio>=0.21.0; extra == 'test'
Requires-Dist: pytest-cov>=4.1.0; extra == 'test'
Requires-Dist: pytest>=7.0.0; extra == 'test'
